dgopy/__init__.py
dgopy-0.0.4.dist-info/METADATA
dgopy-0.0.4.dist-info/WHEEL
dgopy-0.0.4.dist-info/top_level.txt
dgopy-0.0.4.dist-info/RECORD
